my_lib/__init__.py
my_lib/attention.py
my_lib_dsci510-0.1.0.dist-info/METADATA
my_lib_dsci510-0.1.0.dist-info/WHEEL
my_lib_dsci510-0.1.0.dist-info/top_level.txt
my_lib_dsci510-0.1.0.dist-info/RECORD
