Metadata-Version: 2.4
Name: my_lib_dsci510
Version: 0.1.0
Summary: A simple demo library with an attention function
Author: Your Name
Requires-Python: >=3.6
Requires-Dist: numpy>=1.20.0
Dynamic: author
Dynamic: requires-dist
Dynamic: requires-python
Dynamic: summary
